randomriver/RandomRiver.py
randomriver/__init__.py
randomriver-0.0.1.dist-info/licenses/LICENSE.md
randomriver-0.0.1.dist-info/METADATA
randomriver-0.0.1.dist-info/WHEEL
randomriver-0.0.1.dist-info/top_level.txt
randomriver-0.0.1.dist-info/RECORD
